singlejson/__about__.py
singlejson/__init__.py
singlejson/fileutils.py
singlejson/pool.py
singlejson/py.typed
singlejson-0.5.2.dist-info/licenses/LICENSE
singlejson-0.5.2.dist-info/METADATA
singlejson-0.5.2.dist-info/WHEEL
singlejson-0.5.2.dist-info/top_level.txt
singlejson-0.5.2.dist-info/RECORD
