Metadata-Version: 2.4
Name: singlejson
Version: 0.5.2
Summary:  Load and save json files as a global object 
Author-email: Qrashi <fritz@vibe.ac>
License-Expression: GPL-3.0-or-later
Project-URL: Homepage, https://github.com/IgnyteX-Labs/singlejson
Project-URL: Issues, https://github.com/IgnyteX-Labs/singlejson/issues
Project-URL: Documentation, https://singlejson.readthedocs.io/
Classifier: Programming Language :: Python :: 3
Classifier: Operating System :: OS Independent
Requires-Python: >=3.10
License-File: LICENSE
Dynamic: license-file
